synapsis_face_preprocessor_lib/DOCUMENTATION.md
synapsis_face_preprocessor_lib/__init__.py
synapsis_face_preprocessor_lib/face_preprocessor.py
synapsis_face_preprocessor_lib/py.typed
synapsis_face_preprocessor_lib-1.0.0.dist-info/METADATA
synapsis_face_preprocessor_lib-1.0.0.dist-info/WHEEL
synapsis_face_preprocessor_lib-1.0.0.dist-info/RECORD
