Metadata-Version: 2.4
Name: synapsis-face-preprocessor-lib
Version: 1.0.0
Summary: Library Synapsis untuk melakukan preprocessing wajah yang fleksibel dan dapat dikonfigurasi untuk berbagai model face embedding.
Author-email: mufid hadi <mufidmove@gmail.com>
Requires-Python: >=3.11
Requires-Dist: opencv-python>=4.12.0.88
